workspace_generator/__init__.py
workspace_generator/cli.py
workspace_generator/generator.py
vscode_workspace_config_generator-1.1.2.dist-info/METADATA
vscode_workspace_config_generator-1.1.2.dist-info/WHEEL
vscode_workspace_config_generator-1.1.2.dist-info/entry_points.txt
vscode_workspace_config_generator-1.1.2.dist-info/top_level.txt
vscode_workspace_config_generator-1.1.2.dist-info/RECORD
