Metadata-Version: 2.1
Name: vscode-workspace-config-generator
Version: 1.1.2
Summary: Generate VS Code workspace files for multi-package projects
Author: Your Name
Author-email: your.email@example.com
Classifier: Programming Language :: Python :: 3
Classifier: License :: OSI Approved :: MIT License
Classifier: Operating System :: OS Independent
Requires-Python: >=3.6
